indentytool/__init__.py
indentytool/indentytool.py
indentytool-0.1.0.dist-info/licenses/LICENSE
indentytool-0.1.0.dist-info/METADATA
indentytool-0.1.0.dist-info/WHEEL
indentytool-0.1.0.dist-info/top_level.txt
indentytool-0.1.0.dist-info/RECORD
