Metadata-Version: 2.4
Name: Indentytool
Version: 0.1.0
Summary: A Python library for generating realistic fake identities
Author: DottSpace12
Author-email: dottspace12@gmail.com
License: Custom::Restricted Use License
Classifier: Programming Language :: Python :: 3
Classifier: License :: OSI Approved :: MIT License
Classifier: Operating System :: OS Independent
Requires-Python: >=3.6
License-File: LICENSE
Dynamic: author
Dynamic: author-email
Dynamic: classifier
Dynamic: description
Dynamic: description-content-type
Dynamic: license
Dynamic: license-file
Dynamic: requires-python
Dynamic: summary
